LICENSE
MANIFEST.in
README.md
setup.cfg
setup.py
flask_webpack_loader/__init__.py
flask_webpack_loader/config.py
flask_webpack_loader/exceptions.py
flask_webpack_loader/loader.py
flask_webpack_loader.egg-info/PKG-INFO
flask_webpack_loader.egg-info/SOURCES.txt
flask_webpack_loader.egg-info/dependency_links.txt
flask_webpack_loader.egg-info/top_level.txt