Metadata-Version: 2.1
Name: flask-webpack-loader
Version: 0.0.2
Summary: Transparently use webpack with flask
Home-page: https://github.com/naivefeeling/flask-webpack-loader.git
Author: naivefeeling
Author-email: feeling.luu@gmail.com
License: UNKNOWN
Download-URL: https://github.com/naivefeeling/flask-webpack-loader/tarball/0.0.2
Keywords: flask,webpack,assets
Platform: UNKNOWN
Classifier: Programming Language :: Python :: 2.7
Classifier: Programming Language :: Python :: 3.6
Classifier: Framework :: Flask
Classifier: Environment :: Web Environment
Classifier: License :: OSI Approved :: MIT License
